{
  "Common": {
    "Version": "Version ({l_version number}).",
    "Cancel": "Avbryt",
    "Confirm": "Bekräfta",
    "ConfirmDelete": "Är du säker på att du vill ta bort '{l_name}'? Denna åtgärd kan inte ångras!"
  },
  "Menu": {
    "File": "Fil",
    "Views": "Visningar",
    "Filter": "Filter|* |Lägg till nytt filter",
    "Help": "Sök efter uppgradering",
    "Open": "Öppna",
    "FromUrl": "Från webbadress",
    "Exit": "Avsluta",
    "ShowOnlyFiltered": "Visa endast filtrerad rad",
    "AddNewFilter": "Lägg till nytt filter",
    "CheckUpgrade": "Sök efter uppgradering",
    "OpenAppDataFolder": "Öppna appdatamappen",
    "About": "Om"
  },
  "Upgrader": {
    "Title": "Ladda ner nu",
    "DownloadNow": "Avsluta och uppgradera nu",
    "UpgradeNow": "Uppgradera vid nästa start",
    "UpgradeNextStartup": "Ignorera den här versionen",
    "IgnoreThisVersion": "Ingen scenariokälla"
  },
  "Scenario": {
    "NoSource": "Filtrera grenar",
    "FilterBranches": "Scenarioinställning",
    "PanelTitle": "Uppdaterar...",
    "Updating": "Scenarionamn:",
    "Creator": {
      "ScenarioName": "Ange scenarionamn",
      "ScenarioNameWatermark": "En scenariokonfiguration kan&apos ;t innehåller något av följande tecken:/\\:*?\"<>|",
      "ScenarioNameValidNameError": "Scenarionamn kan inte vara null eller medan mellanslag.",
      "ScenarioNameValidNull": "Det finns redan en befintlig scenariokonfiguration.",
      "ScenarioNameValidExist": "Scenarioförråd: ",
      "ScenarioRepo": "Ange scenarioförråd",
      "ScenarioRepoWatermark": "Scenarioförråd kan inte vara null eller medan mellanslag.",
      "ScenarioRepoValidNull": "Scenarioförgrening:",
      "ScenarioBranch": "Ange scenarioförgrening",
      "ScenarioBranchWatermark": "Scenarioförgrening kan inte vara null eller medan mellanslag.",
      "ScenarioBranchValidNull": "Läser nu in... "
    }
  },
  "Loading": {
    "OpenFileStart": "Laddar {l_file}.",
    "LoadingFile": "Laddar {l_file}."
  },
  "OpenFileDialog": {
    "PickLog": "Välj loggar",
    "SupportedLogs": "loggar som stöds"
  }
}